ndlib/__init__.py
ndlib/utils.py
ndlib/models/CompositeModel.py
ndlib/models/ContinuousModel.py
ndlib/models/ContinuousModelRunner.py
ndlib/models/DiffusionModel.py
ndlib/models/DynamicCompositeModel.py
ndlib/models/DynamicCompostiteModel.py
ndlib/models/DynamicDiffusionModel.py
ndlib/models/ModelConfig.py
ndlib/models/__init__.py
ndlib/models/compartments/Compartment.py
ndlib/models/compartments/ConditionalComposition.py
ndlib/models/compartments/CountDown.py
ndlib/models/compartments/EdgeCategoricalAttribute.py
ndlib/models/compartments/EdgeNumericalAttribute.py
ndlib/models/compartments/EdgeStochastic.py
ndlib/models/compartments/NodeCategoricalAttribute.py
ndlib/models/compartments/NodeNumericalAttribute.py
ndlib/models/compartments/NodeNumericalVariable.py
ndlib/models/compartments/NodeStochastic.py
ndlib/models/compartments/NodeThreshold.py
ndlib/models/compartments/__init__.py
ndlib/models/dynamic/DynKerteszThresholdModel.py
ndlib/models/dynamic/DynProfileModel.py
ndlib/models/dynamic/DynProfileThresholdModel.py
ndlib/models/dynamic/DynSIModel.py
ndlib/models/dynamic/DynSIRModel.py
ndlib/models/dynamic/DynSISModel.py
ndlib/models/dynamic/__init__.py
ndlib/models/epidemics/GeneralThresholdModel.py
ndlib/models/epidemics/GeneralisedThresholdModel.py
ndlib/models/epidemics/ICEModel.py
ndlib/models/epidemics/ICEPModel.py
ndlib/models/epidemics/ICPModel.py
ndlib/models/epidemics/IndependentCascadesModel.py
ndlib/models/epidemics/KerteszThresholdModel.py
ndlib/models/epidemics/ProfileModel.py
ndlib/models/epidemics/ProfileThresholdModel.py
ndlib/models/epidemics/SEIRModel.py
ndlib/models/epidemics/SEIR_ct_Model.py
ndlib/models/epidemics/SEISModel.py
ndlib/models/epidemics/SEIS_ct_Model.py
ndlib/models/epidemics/SIModel.py
ndlib/models/epidemics/SIRModel.py
ndlib/models/epidemics/SISModel.py
ndlib/models/epidemics/SWIRModel.py
ndlib/models/epidemics/TDMethod.py
ndlib/models/epidemics/ThresholdModel.py
ndlib/models/epidemics/UTLDRModel.py
ndlib-5.1.0.dist-info/LICENSE
ndlib-5.1.0.dist-info/METADATA
ndlib-5.1.0.dist-info/WHEEL
ndlib-5.1.0.dist-info/entry_points.txt
ndlib-5.1.0.dist-info/top_level.txt
ndlib-5.1.0.dist-info/RECORD
