Metadata-Version: 2.1
Name: ndlib
Version: 5.1.0
Summary: Network Diffusion Library
Home-page: https://github.com/GiulioRossetti/ndlib
Author: Giulio Rossetti
Author-email: giulio.rossetti@gmail.com
License: BSD-Clause-2
Keywords: epidemics opinion-dynamics simulator complex-networks
Platform: UNKNOWN
Classifier: Development Status :: 5 - Production/Stable
Classifier: Intended Audience :: Developers
Classifier: Topic :: Software Development :: Build Tools
Classifier: License :: OSI Approved :: BSD License
Classifier: Operating System :: OS Independent
Classifier: Programming Language :: Python
Classifier: Programming Language :: Python :: 3
Requires-Dist: netdispatch
Requires-Dist: python-igraph
Requires-Dist: numpy
Requires-Dist: networkx
Requires-Dist: dynetx
Requires-Dist: scipy
Requires-Dist: bokeh
Requires-Dist: future
